unittest2pytest/__init__.py
unittest2pytest/__main__.py
unittest2pytest/utils.py
unittest2pytest/fixes/__init__.py
unittest2pytest/fixes/fix_remove_class.py
unittest2pytest/fixes/fix_self_assert.py
unittest2pytest-0.5.dist-info/AUTHORS.txt
unittest2pytest-0.5.dist-info/COPYING-GPLv3.txt
unittest2pytest-0.5.dist-info/METADATA
unittest2pytest-0.5.dist-info/WHEEL
unittest2pytest-0.5.dist-info/entry_points.txt
unittest2pytest-0.5.dist-info/top_level.txt
unittest2pytest-0.5.dist-info/RECORD
