Metadata-Version: 2.1
Name: unittest2pytest
Version: 0.5
Summary: Convert unittest test-cases to pytest
Home-page: https://github.com/pytest-dev/unittest2pytest
Author: Hartmut Goebel
Author-email: h.goebel@crazy-compilers.com
License: GPLv3+
Classifier: Development Status :: 4 - Beta
Classifier: Environment :: Console
Classifier: Intended Audience :: Developers
Classifier: License :: OSI Approved :: GNU General Public License v3 or later (GPLv3+)
Classifier: Operating System :: OS Independent
Classifier: Programming Language :: Python
Classifier: Programming Language :: Python :: 3
Classifier: Programming Language :: Python :: 3 :: Only
Classifier: Programming Language :: Python :: 3.9
Classifier: Programming Language :: Python :: 3.10
Classifier: Programming Language :: Python :: 3.11
Classifier: Programming Language :: Python :: 3.12
Classifier: Topic :: Software Development
Classifier: Topic :: Utilities
Requires-Python: >=3.9
License-File: COPYING-GPLv3.txt
License-File: AUTHORS.txt
